[{"algorithm":"weka.AdaBoostM1_DecisionStump(14)","breast_w":0.990754,"credit_a":0.934845,"credit_g":0.770824,"diabetes":0.824082,"electricity":0.869234,"gina_agnostic":0.926233,"irish":1.0,"jm1":0.716893,"kc1":0.784733,"kr_vs_kp":0.992411,"MagicTelescope":0.886538,"monks_problems_1":0.721663,"monks_problems_2":0.564373,"monks_problems_3":0.983213,"mozilla4":0.957486,"mushroom":0.999999,"musk":0.995805,"pc1":0.853638,"pc3":0.803644,"pc4":0.927956,"profb":0.641039,"scene":0.989475,"sick":0.983889,"spambase":0.977421,"sylva_agnostic":0.998722,"tic_tac_toe":0.975899},{"algorithm":"weka.AttributeSelectedClassifier_CfsSubsetEval_BestFirst_AdaBoostM1_DecisionStump(3)","breast_w":0.990754,"credit_a":0.928067,"credit_g":0.752895,"diabetes":0.824903,"electricity":0.831955,"gina_agnostic":0.90976,"irish":1.0,"jm1":0.716354,"kc1":0.782884,"kr_vs_kp":0.970994,"MagicTelescope":0.853536,"monks_problems_1":0.721663,"monks_problems_2":0.53199,"monks_problems_3":0.980087,"mozilla4":0.955458,"mushroom":0.992068,"musk":0.960264,"pc1":0.820736,"pc3":0.80662,"pc4":0.906913,"profb":0.616321,"scene":0.980689,"sick":0.957136,"spambase":0.975114,"sylva_agnostic":0.998078,"tic_tac_toe":0.770764},{"algorithm":"weka.AttributeSelectedClassifier_CfsSubsetEval_BestFirst_HoeffdingTree(3)","breast_w":0.978764,"credit_a":0.766476,"credit_g":0.750788,"diabetes":0.818951,"electricity":0.645586,"gina_agnostic":0.838569,"irish":1.0,"jm1":0.579173,"kc1":0.495732,"kr_vs_kp":0.961614,"MagicTelescope":0.835608,"monks_problems_1":0.699006,"monks_problems_2":0.490998,"monks_problems_3":0.978488,"mozilla4":0.937569,"mushroom":0.992292,"musk":0.999986,"pc1":0.485597,"pc3":0.499252,"pc4":0.654128,"profb":0.576486,"scene":0.49835,"sick":0.935051,"spambase":0.632146,"sylva_agnostic":0.985223,"tic_tac_toe":0.774433},{"algorithm":"weka.AttributeSelectedClassifier_CfsSubsetEval_BestFirst_IBk(3)","breast_w":0.976621,"credit_a":0.826056,"credit_g":0.678443,"diabetes":0.660746,"electricity":0.6915,"gina_agnostic":0.884584,"irish":0.994426,"jm1":0.627986,"kc1":0.685296,"kr_vs_kp":0.970021,"MagicTelescope":0.750301,"monks_problems_1":0.653771,"monks_problems_2":0.495361,"monks_problems_3":0.985961,"mozilla4":0.933014,"mushroom":0.993127,"musk":0.999999,"pc1":0.732162,"pc3":0.65425,"pc4":0.840002,"profb":0.58228,"scene":0.925273,"sick":0.864679,"spambase":0.911414,"sylva_agnostic":0.951352,"tic_tac_toe":0.871444},{"algorithm":"weka.AttributeSelectedClassifier_CfsSubsetEval_BestFirst_J48(4)","breast_w":0.958896,"credit_a":0.884654,"credit_g":0.728521,"diabetes":0.783806,"electricity":0.844663,"gina_agnostic":0.88505,"irish":1.0,"jm1":0.663947,"kc1":0.740142,"kr_vs_kp":0.959444,"MagicTelescope":0.865072,"monks_problems_1":0.683764,"monks_problems_2":0.490998,"monks_problems_3":0.98929,"mozilla4":0.942439,"mushroom":0.992303,"musk":0.999999,"pc1":0.735308,"pc3":0.649098,"pc4":0.839956,"profb":0.486582,"scene":0.896221,"sick":0.920525,"spambase":0.950074,"sylva_agnostic":0.975405,"tic_tac_toe":0.775937},{"algorithm":"weka.AttributeSelectedClassifier_CfsSubsetEval_BestFirst_JRip(3)","breast_w":0.966058,"credit_a":0.883132,"credit_g":0.647831,"diabetes":0.722743,"electricity":0.785413,"gina_agnostic":0.903922,"irish":1.0,"jm1":0.56922,"kc1":0.604645,"kr_vs_kp":0.940586,"MagicTelescope":0.787486,"monks_problems_1":0.713,"monks_problems_2":0.496946,"monks_problems_3":0.981386,"mozilla4":0.89708,"mushroom":0.987817,"musk":0.999607,"pc1":0.617122,"pc3":0.549869,"pc4":0.629508,"profb":0.514823,"scene":0.880386,"sick":0.902103,"spambase":0.923844,"sylva_agnostic":0.964178,"tic_tac_toe":0.726459},{"algorithm":"weka.AttributeSelectedClassifier_CfsSubsetEval_BestFirst_Logistic(3)","breast_w":0.99393,"credit_a":0.924418,"credit_g":0.754998,"diabetes":0.821358,"electricity":0.801806,"gina_agnostic":0.926826,"irish":0.989589,"jm1":0.713012,"kc1":0.79183,"kr_vs_kp":0.969472,"MagicTelescope":0.819523,"monks_problems_1":0.704499,"monks_problems_2":0.525439,"monks_problems_3":0.983168,"mozilla4":0.894651,"mushroom":0.992497,"musk":1.0,"pc1":0.742185,"pc3":0.793427,"pc4":0.824372,"profb":0.633655,"scene":0.977868,"sick":0.939448,"spambase":0.966444,"sylva_agnostic":0.997657,"tic_tac_toe":0.77075},{"algorithm":"weka.AttributeSelectedClassifier_CfsSubsetEval_BestFirst_MultilayerPerceptron(3)","breast_w":0.970311,"credit_a":0.881375,"credit_g":0.730098,"diabetes":0.817821,"electricity":0.78305,"gina_agnostic":0.868302,"irish":1.0,"jm1":0.687799,"kc1":0.767455,"kr_vs_kp":0.971235,"MagicTelescope":0.817542,"monks_problems_1":0.720938,"monks_problems_2":0.631117,"monks_problems_3":0.988422,"mozilla4":0.905201,"mushroom":0.992131,"musk":0.999999,"pc1":0.65882,"pc3":0.801604,"pc4":0.779045,"profb":0.628777,"scene":0.957664,"sick":0.897197,"spambase":0.957873,"sylva_agnostic":0.98875,"tic_tac_toe":0.725425},{"algorithm":"weka.AttributeSelectedClassifier_CfsSubsetEval_BestFirst_NaiveBayes(3)","breast_w":0.979837,"credit_a":0.904504,"credit_g":0.750283,"diabetes":0.821358,"electricity":0.794951,"gina_agnostic":0.874943,"irish":0.999579,"jm1":0.66604,"kc1":0.746946,"kr_vs_kp":0.966954,"MagicTelescope":0.795514,"monks_problems_1":0.711143,"monks_problems_2":0.52394,"monks_problems_3":0.978488,"mozilla4":0.874409,"mushroom":0.991181,"musk":0.999999,"pc1":0.676772,"pc3":0.786859,"pc4":0.807047,"profb":0.64065,"scene":0.880016,"sick":0.934732,"spambase":0.946226,"sylva_agnostic":0.996628,"tic_tac_toe":0.774433},{"algorithm":"weka.AttributeSelectedClassifier_CfsSubsetEval_BestFirst_RandomForest(3)","breast_w":0.991656,"credit_a":0.908642,"credit_g":0.723614,"diabetes":0.801784,"electricity":0.884172,"gina_agnostic":0.964941,"irish":0.999692,"jm1":0.745084,"kc1":0.813533,"kr_vs_kp":0.969851,"MagicTelescope":0.88756,"monks_problems_1":0.652807,"monks_problems_2":0.501745,"monks_problems_3":0.989472,"mozilla4":0.970476,"mushroom":0.993129,"musk":0.999999,"pc1":0.853827,"pc3":0.83058,"pc4":0.903801,"profb":0.599505,"scene":0.963512,"sick":0.942275,"spambase":0.978157,"sylva_agnostic":0.997302,"tic_tac_toe":0.872662},{"algorithm":"weka.AttributeSelectedClassifier_CfsSubsetEval_BestFirst_REPTree(4)","breast_w":0.963439,"credit_a":0.877357,"credit_g":0.724426,"diabetes":0.786784,"electricity":0.848016,"gina_agnostic":0.913975,"irish":1.0,"jm1":0.698977,"kc1":0.768729,"kr_vs_kp":0.958776,"MagicTelescope":0.86423,"monks_problems_1":0.683764,"monks_problems_2":0.469559,"monks_problems_3":0.988865,"mozilla4":0.956301,"mushroom":0.991763,"musk":0.999999,"pc1":0.733074,"pc3":0.706544,"pc4":0.874855,"profb":0.564657,"scene":0.92466,"sick":0.918352,"spambase":0.958133,"sylva_agnostic":0.989519,"tic_tac_toe":0.750221},{"algorithm":"weka.AttributeSelectedClassifier_CfsSubsetEval_BestFirst_SGD(1)","breast_w":0.961895,"credit_a":0.858115,"credit_g":0.611905,"diabetes":0.732507,"electricity":0.74087,"gina_agnostic":0.860702,"irish":0.989209,"jm1":0.502137,"kc1":0.522577,"kr_vs_kp":0.93989,"MagicTelescope":0.740464,"monks_problems_1":0.746403,"monks_problems_2":0.5,"monks_problems_3":0.980185,"mozilla4":0.832595,"mushroom":0.989785,"musk":0.999017,"pc1":0.5,"pc3":0.5,"pc4":0.54619,"profb":0.507812,"scene":0.919008,"sick":0.64902,"spambase":0.887648,"sylva_agnostic":0.953132,"tic_tac_toe":0.673188},{"algorithm":"weka.AttributeSelectedClassifier_CfsSubsetEval_BestFirst_SMO_PolyKernel(3)","breast_w":0.962986,"credit_a":0.861695,"credit_g":0.574762,"diabetes":0.713194,"electricity":0.736766,"gina_agnostic":0.861379,"irish":0.989209,"jm1":0.500237,"kc1":0.500973,"kr_vs_kp":0.939563,"MagicTelescope":0.738724,"monks_problems_1":0.746403,"monks_problems_2":0.5,"monks_problems_3":0.969768,"mozilla4":0.835656,"mushroom":0.989785,"musk":0.999017,"pc1":0.5,"pc3":0.5,"pc4":0.516463,"profb":0.502232,"scene":0.924555,"sick":0.5,"spambase":0.845121,"sylva_agnostic":0.944288,"tic_tac_toe":0.666182},{"algorithm":"weka.HoeffdingTree(4)","breast_w":0.978764,"credit_a":0.740736,"credit_g":0.779105,"diabetes":0.775903,"electricity":0.670479,"gina_agnostic":0.783814,"irish":1.0,"jm1":0.527941,"kc1":0.495732,"kr_vs_kp":0.981852,"MagicTelescope":0.606336,"monks_problems_1":0.671297,"monks_problems_2":0.490998,"monks_problems_3":0.979787,"mozilla4":0.941515,"mushroom":0.999458,"musk":0.999997,"pc1":0.485597,"pc3":0.499252,"pc4":0.495506,"profb":0.579052,"scene":0.49835,"sick":0.572214,"spambase":0.645701,"sylva_agnostic":0.957224,"tic_tac_toe":0.747604},{"algorithm":"weka.IBk(7)","breast_w":0.976621,"credit_a":0.80897,"credit_g":0.640714,"diabetes":0.672478,"electricity":0.788704,"gina_agnostic":0.826702,"irish":0.993292,"jm1":0.634889,"kc1":0.73278,"kr_vs_kp":0.987484,"MagicTelescope":0.778521,"monks_problems_1":1.0,"monks_problems_2":0.873301,"monks_problems_3":0.969096,"mozilla4":0.877263,"mushroom":1.0,"musk":0.9938,"pc1":0.712172,"pc3":0.643309,"pc4":0.749122,"profb":0.41478,"scene":0.91569,"sick":0.810167,"spambase":0.90924,"sylva_agnostic":0.909825,"tic_tac_toe":0.999856},{"algorithm":"weka.J48(33)","breast_w":0.958896,"credit_a":0.879147,"credit_g":0.639755,"diabetes":0.744343,"electricity":0.930252,"gina_agnostic":0.869884,"irish":1.0,"jm1":0.669386,"kc1":0.676099,"kr_vs_kp":0.998611,"MagicTelescope":0.863913,"monks_problems_1":0.998945,"monks_problems_2":0.55491,"monks_problems_3":0.990236,"mozilla4":0.9521,"mushroom":1.0,"musk":0.999999,"pc1":0.683385,"pc3":0.604368,"pc4":0.79648,"profb":0.566476,"scene":0.971373,"sick":0.95798,"spambase":0.945755,"sylva_agnostic":0.95292,"tic_tac_toe":0.899431},{"algorithm":"weka.JRip(5)","breast_w":0.966058,"credit_a":0.878871,"credit_g":0.626693,"diabetes":0.726944,"electricity":0.871034,"gina_agnostic":0.916555,"irish":1.0,"jm1":0.571184,"kc1":0.626181,"kr_vs_kp":0.994112,"MagicTelescope":0.821338,"monks_problems_1":0.996655,"monks_problems_2":0.470087,"monks_problems_3":0.982358,"mozilla4":0.918581,"mushroom":1.0,"musk":0.986784,"pc1":0.597591,"pc3":0.565993,"pc4":0.720119,"profb":0.590372,"scene":0.858848,"sick":0.936008,"spambase":0.92889,"sylva_agnostic":0.974032,"tic_tac_toe":0.969598},{"algorithm":"weka.Logistic(6)","breast_w":0.99393,"credit_a":0.907443,"credit_g":0.78485,"diabetes":0.83003,"electricity":0.827344,"gina_agnostic":0.752764,"irish":0.994167,"jm1":0.712997,"kc1":0.797317,"kr_vs_kp":0.995569,"MagicTelescope":0.839137,"monks_problems_1":0.694775,"monks_problems_2":0.545213,"monks_problems_3":0.984891,"mozilla4":0.886733,"mushroom":1.0,"musk":0.999015,"pc1":0.812456,"pc3":0.819307,"pc4":0.914795,"profb":0.771898,"scene":0.930669,"sick":0.938698,"spambase":0.971506,"sylva_agnostic":0.994986,"tic_tac_toe":0.996593},{"algorithm":"weka.MultilayerPerceptron(4)","breast_w":0.970311,"credit_a":0.870264,"credit_g":0.698424,"diabetes":0.819496,"electricity":0.780387,"gina_agnostic":0.866775,"irish":1.0,"jm1":0.673685,"kc1":0.750175,"kr_vs_kp":0.978658,"MagicTelescope":0.826207,"monks_problems_1":0.787466,"monks_problems_2":0.768895,"monks_problems_3":0.980975,"mozilla4":0.905394,"mushroom":0.997225,"musk":0.999656,"pc1":0.660834,"pc3":0.758223,"pc4":0.8083,"profb":0.703434,"scene":0.965087,"sick":0.908634,"spambase":0.942332,"sylva_agnostic":0.986801,"tic_tac_toe":0.973493},{"algorithm":"weka.NaiveBayes(13)","breast_w":0.979837,"credit_a":0.896216,"credit_g":0.781452,"diabetes":0.813597,"electricity":0.789515,"gina_agnostic":0.783372,"irish":0.999384,"jm1":0.614346,"kc1":0.736399,"kr_vs_kp":0.951281,"MagicTelescope":0.756822,"monks_problems_1":0.709694,"monks_problems_2":0.544636,"monks_problems_3":0.979787,"mozilla4":0.829216,"mushroom":0.998043,"musk":0.859154,"pc1":0.626177,"pc3":0.75335,"pc4":0.824059,"profb":0.666763,"scene":0.775983,"sick":0.925577,"spambase":0.837867,"sylva_agnostic":0.995974,"tic_tac_toe":0.747604},{"algorithm":"weka.RandomForest(9)","breast_w":0.991656,"credit_a":0.924635,"credit_g":0.768002,"diabetes":0.82997,"electricity":0.978805,"gina_agnostic":0.980495,"irish":0.999692,"jm1":0.755092,"kc1":0.830118,"kr_vs_kp":0.999129,"MagicTelescope":0.937194,"monks_problems_1":1.0,"monks_problems_2":0.809027,"monks_problems_3":0.990353,"mozilla4":0.98378,"mushroom":1.0,"musk":0.99994,"pc1":0.861371,"pc3":0.853452,"pc4":0.946333,"profb":0.542132,"scene":0.952023,"sick":0.99664,"spambase":0.988118,"sylva_agnostic":0.998476,"tic_tac_toe":0.997652},{"algorithm":"weka.REPTree(15)","breast_w":0.963439,"credit_a":0.875558,"credit_g":0.714648,"diabetes":0.799179,"electricity":0.931672,"gina_agnostic":0.905953,"irish":1.0,"jm1":0.695465,"kc1":0.768973,"kr_vs_kp":0.997912,"MagicTelescope":0.88591,"monks_problems_1":0.992172,"monks_problems_2":0.508812,"monks_problems_3":0.989596,"mozilla4":0.961294,"mushroom":0.999997,"musk":0.999999,"pc1":0.743129,"pc3":0.73194,"pc4":0.87168,"profb":0.561499,"scene":0.948885,"sick":0.950712,"spambase":0.955748,"sylva_agnostic":0.983544,"tic_tac_toe":0.848678},{"algorithm":"weka.SGD(4)","breast_w":0.961895,"credit_a":0.859084,"credit_g":0.707619,"diabetes":0.730239,"electricity":0.741753,"gina_agnostic":0.79887,"irish":0.989209,"jm1":0.503751,"kc1":0.551008,"kr_vs_kp":0.970871,"MagicTelescope":0.750002,"monks_problems_1":0.746403,"monks_problems_2":0.5,"monks_problems_3":0.988865,"mozilla4":0.83261,"mushroom":1.0,"musk":0.999017,"pc1":0.512503,"pc3":0.5,"pc4":0.642161,"profb":0.670759,"scene":0.961698,"sick":0.717532,"spambase":0.916109,"sylva_agnostic":0.978703,"tic_tac_toe":0.975904},{"algorithm":"weka.SMO_PolyKernel(11)","breast_w":0.962986,"credit_a":0.859084,"credit_g":0.66881,"diabetes":0.712925,"electricity":0.735355,"gina_agnostic":0.831234,"irish":0.989209,"jm1":0.502137,"kc1":0.517976,"kr_vs_kp":0.961731,"MagicTelescope":0.746909,"monks_problems_1":0.746403,"monks_problems_2":0.5,"monks_problems_3":0.974977,"mozilla4":0.838025,"mushroom":1.0,"musk":0.999017,"pc1":0.499516,"pc3":0.5,"pc4":0.557817,"profb":0.640625,"scene":0.969838,"sick":0.5,"spambase":0.888103,"sylva_agnostic":0.984235,"tic_tac_toe":0.975904}]